flor/__init__.py
flor/filter.py
flor/fnv.py
Flor-1.1.3.dist-info/LICENSE
Flor-1.1.3.dist-info/METADATA
Flor-1.1.3.dist-info/WHEEL
Flor-1.1.3.dist-info/top_level.txt
Flor-1.1.3.dist-info/RECORD
