Metadata-Version: 2.1
Name: Flor
Version: 1.1.3
Summary: Flor - An efficient Bloom filter implementation in Python
Home-page: https://github.com/DCSO/flor
Author: Andreas Dewes - DCSO GmbH
Author-email: andreas.dewes@dcso.de
License: BSD3
Platform: UNKNOWN
